{
  "teamId": 387838,
  "freeTransfers": 3,
  "hitCost": 4,
  "chips": {
    "wildcard": false,
    "freeHit": true,
    "benchBoost": false
  },
  "historyWindow": 4,
  "minimumRecentMinutes": 180,
  "minimumChanceOfPlaying": 50,
  "minimumSeasonMinutes": 600,
  "budget": 1000,
  "squadSize": {
    "GK": 2,
    "DEF": 5,
    "MID": 5,
    "FWD": 3
  },
  "picksPerPosition": {
    "GK": 2,
    "DEF": 8,
    "MID": 8,
    "FWD": 5
  },
  "common": {
    "availability": 2,
    "fixtureEase": 3,
    "epNext": 5,
    "form": 1.5,
    "pointsPerGame": 6,
    "seasonMinutes": 0.5,
    "recentMinutesRatio": 1.5,
    "recentPointsPer90": 3,
    "recentExpectedGoalsPer90": 0.8,
    "recentExpectedAssistsPer90": 0.8,
    "recentCleanSheetRate": 1,
    "recentBonusPer90": 0.5,
    "value": 1.5
  },
  "byPosition": {
    "GK": {
      "recentCleanSheetRate": 1.5,
      "recentSavesPer90": 1,
      "recentGoalsConcededPer90": -0.5
    },
    "DEF": {
      "recentCleanSheetRate": 1.2,
      "recentExpectedGoalsPer90": 0.6,
      "recentExpectedAssistsPer90": 0.5,
      "recentGoalsConcededPer90": -0.5
    },
    "MID": {
      "recentExpectedGoalsPer90": 0.8,
      "recentExpectedAssistsPer90": 0.8,
      "recentCleanSheetRate": 0.3
    },
    "FWD": {
      "recentExpectedGoalsPer90": 1,
      "recentExpectedAssistsPer90": 0.4
    }
  }
}
